_custom_build.py
forbiditerative/__version__.py
forbiditerative/copy_plans.py
forbiditerative/fast-downward.py
forbiditerative/plan.py
forbiditerative/timers.py
forbiditerative/__init__.py
forbiditerative/planner_call.py
forbiditerative/planners.py
forbiditerative/builds/release/bin/preprocess
forbiditerative/builds/release/bin/downward
forbiditerative/builds/release/bin/translate/graph.py
forbiditerative/builds/release/bin/translate/simplify.py
forbiditerative/builds/release/bin/translate/instantiate.py
forbiditerative/builds/release/bin/translate/normalize.py
forbiditerative/builds/release/bin/translate/translate.py
forbiditerative/builds/release/bin/translate/invariant_finder.py
forbiditerative/builds/release/bin/translate/build_model.py
forbiditerative/builds/release/bin/translate/abstract_structure_module.py
forbiditerative/builds/release/bin/translate/invariants.py
forbiditerative/builds/release/bin/translate/sas_tasks.py
forbiditerative/builds/release/bin/translate/pddl_to_prolog.py
forbiditerative/builds/release/bin/translate/greedy_join.py
forbiditerative/builds/release/bin/translate/options.py
forbiditerative/builds/release/bin/translate/variable_order.py
forbiditerative/builds/release/bin/translate/fact_groups.py
forbiditerative/builds/release/bin/translate/split_rules.py
forbiditerative/builds/release/bin/translate/sccs.py
forbiditerative/builds/release/bin/translate/axiom_rules.py
forbiditerative/builds/release/bin/translate/timers.py
forbiditerative/builds/release/bin/translate/constraints.py
forbiditerative/builds/release/bin/translate/tools.py
forbiditerative/builds/release/bin/translate/pddl/f_expression.py
forbiditerative/builds/release/bin/translate/pddl/pddl_types.py
forbiditerative/builds/release/bin/translate/pddl/tasks.py
forbiditerative/builds/release/bin/translate/pddl/functions.py
forbiditerative/builds/release/bin/translate/pddl/axioms.py
forbiditerative/builds/release/bin/translate/pddl/effects.py
forbiditerative-1.1.4.dist-info/WHEEL
forbiditerative-1.1.4.dist-info/top_level.txt
forbiditerative-1.1.4.dist-info/METADATA
forbiditerative-1.1.4.dist-info/RECORD
forbiditerative-1.1.4.dist-info/licenses/LICENSE
forbiditerative-1.1.4.dist-info/licenses/LICENSE.md
