Metadata-Version: 2.4
Name: forbiditerative
Version: 1.1.4
Summary: Forbid-Iterative (FI) Planner is an Automated PDDL based planner that includes planners for top-k, top-quality, and diverse computational tasks.
Author-email: Michael Katz <michael.katz1@ibm.com>
License:     Forbid-Iterative (FI) Planner is an Automated PDDL based planner that 
Project-URL: Homepage, https://github.com/IBM/forbiditerative
Keywords: planning
Classifier: License :: OSI Approved :: GNU General Public License v3 (GPLv3)
Requires-Python: >=3.8
License-File: LICENSE
License-File: LICENSE.md
Dynamic: license-file
